{"Episode": 76, "_timestamp": 1719490817.3111959, "_runtime": 129.38998079299927, "_step": 3937, "Ep_Total_Reward": -1.8643287746864416, "Ep_Collision_Count": 0, "Ep_Min_Time_To_Collision": 49, "Ep_Wall_Collision_Count": 0, "Ep_Obstacle_Collision_Count": 0, "Ep_Human_Collision_Count": 0, "Ep_Collision_Rate": 0.0, "Ep_Wall_Collision_Rate": 0.0, "Ep_Obstacle_Collision_Rate": 0.0, "Ep_Human_Collision_Rate": 0.0, "Ep_Path_Length": 50, "Ep_Stalled_Time": 0, "Ep_Discomfort": 0.0, "Ep_Avg_Human_Distance": 305.60009401284805, "Ep_Closest_Human_Distance": 0, "Ep_Close_Calls": 0, "Ep_Group_Inhibition": 0.0, "Avg_Collision_Rate": 0.0, "Avg_Min_Time_To_Collision": 48.16883116883117, "Avg_Wall_Collision_Rate": 0.0, "Avg_Obstacle_Collision_Rate": 0.0, "Avg_Human_Collision_Rate": 0.0, "Avg_Path_Length": 0.6493506493506493, "Avg_Stalled_Time": 0.0, "Avg_Discomfort": 0.0, "Avg_Human_Distance": 292.5296921447559, "Avg_Closest_Human_Distance": 0.0, "Avg_Group_Inhibition_Rate": 0.0, "Reward": 6.874875009368907, "Total_Reward": -1.8643287746864416, "TimeOut": 75, "_wandb": {"runtime": 129}}